{
  "case_id": "CONST-2022-0138",
  "case_type": "刑事補償",
  "title": "元被告人 v. 国家",
  "date": "2022-07-15",
  "charges": [
    "憲法第76条に基づく刑事補償請求"
  ],
  "verdict": "認容",
  "sentence": "補償金の支払い命令",
  "legal_principles": [
    "刑事補償請求権",
    "冤罪被害の救済"
  ],
  "summary": "元被告人が、無罪判決確定後に長期拘禁に対する刑事補償を求めた事案である。",
  "reasoning": "裁判所は、刑事補償は憲法上の権利であり、拘禁期間に応じた十分な補償が必要であると判断した。",
  "referenced_statutes": [
    "憲法第76条",
    "憲法第24条",
    "憲法第39条"
  ],
  "reasoning_detailed": "【認定事実】\n元被告人が、無罪判決確定後に長期拘禁に対する刑事補償を求めた事案である。\n本件で審理の対象となった訴因は、憲法第76条に基づく刑事補償請求である。\n\n【適用法令とその趣旨】\n本件の判断において中心となる規定は憲法第76条である。同条は、刑事補償請求権を趣旨とするものであり、その文言および立法目的に照らして要件を解釈する必要がある。あわせて憲法第24条、憲法第39条の適用関係についても検討を要する。\n\n【法的判断】\n本件では、刑事補償請求権、冤罪被害の救済が主たる争点となる。認定した事実をこれらの法的観点に照らして検討すると、被告人（被告）の行為態様、主観的要素および結果との因果関係について、前記法令の定める要件への当てはめを慎重に行うべきである。\n\n【結論】\n以上の事情を総合的に考慮し、主文のとおり補償金の支払い命令。犯行の動機・態様の悪質性、結果の重大性、被害回復の有無、被告人の反省の情その他一切の情状を斟酌した結果である。"
}